tkinter_kit/__init__.py
tkinter_kit/func.py
tkinter_kit-0.1.0.dist-info/METADATA
tkinter_kit-0.1.0.dist-info/WHEEL
tkinter_kit-0.1.0.dist-info/licenses/LICENSE
tkinter_kit-0.1.0.dist-info/RECORD
