Metadata-Version: 2.1
Name: tkinter_kit
Version: 0.1.0
Summary: A package with some helpful tkinter functions! In this version, import tkinter_kit.func becomes simply import tkinter_kit.
Project-URL: Homepage, https://pypi.org/project/tkinter-kit/
Project-URL: Issues, https://github.com/KpihX/tkinter_kit/issues
Project-URL: Repository, https://github.com/KpihX/tkinter_kit.git
Author-email: KpihX <kapoivha@gmail.com>
Maintainer-email: KpihX <kapoivha@gmail.com>
License: MIT License
License-File: LICENSE
Keywords: frame,functions,scroll,tkinter,window
Classifier: Development Status :: 4 - Beta
Classifier: Intended Audience :: Developers
Classifier: License :: OSI Approved :: MIT License
Classifier: Operating System :: OS Independent
Classifier: Programming Language :: Python :: 3
Requires-Python: >=3.8
